nonebot_mockingbird_plugin/__init__.py
nonebot_mockingbird_plugin/resources/encoder.pt
nonebot_mockingbird_plugin/resources/g_hifigan.pt
nonebot_mockingbird_plugin-0.0.2.dist-info/LICENSE.txt
nonebot_mockingbird_plugin-0.0.2.dist-info/WHEEL
nonebot_mockingbird_plugin-0.0.2.dist-info/METADATA
nonebot_mockingbird_plugin-0.0.2.dist-info/RECORD
