Metadata-Version: 2.1
Name: nonebot-mockingbird-plugin
Version: 0.0.2
Summary: A Nonebot Use Version for MockingBird
Home-page: https://github.com/babysor/MockingBird
License: LICENSE
Keywords: MockingBird,python
Author: Alex Newton
Author-email: sharenfan222@gmail.com
Requires-Python: >=3.9,<4.0
Classifier: License :: Other/Proprietary License
Classifier: Programming Language :: Python :: 3
Classifier: Programming Language :: Python :: 3.10
Classifier: Programming Language :: Python :: 3.9
Requires-Dist: MockingBirdOnlyForUse
Requires-Dist: nonebot2 (>=2.0.0b1,<3.0.0)
Project-URL: Repository, https://github.com/Diaosi1111/nonebot_mockingbird_plugin
